{
  "company": "Mozilla Corporation",
  "app_or_service": "Firefox",
  "policy_url": "https://www.mozilla.org/en-US/privacy/firefox/",
  "policy_last_updated": "Not stated",
  "scraped_date": "2026-03-20",
  "category": "Browsers",
  "data_collected": {
    "types": [
      "Browser usage statistics (opt-in telemetry)",
      "Crash reports (opt-in)",
      "Device and browser version information",
      "Firefox Sync data (if enabled)",
      "Search queries (only if using Mozilla-partnered search engine)",
      "Website and URL data (limited)",
      "IP address",
      "Installation and update information"
    ],
    "sensitive_types": [],
    "count": 8,
    "sensitive_count": 0,
    "source_quote": "Based on training knowledge — verify against live policy"
  },
  "purposes_of_collection": {
    "purposes": [
      "Improving Firefox features and performance",
      "Understanding user behavior and preferences",
      "Identifying and fixing crashes and bugs",
      "Combating fraud and abuse",
      "Research and development"
    ],
    "source_quote": "Based on training knowledge — verify against live policy"
  },
  "data_practices": {
    "sold_to_third_parties": {
      "value": false,
      "source_quote": "Based on training knowledge — verify against live policy"
    },
    "shared_for_advertising": {
      "value": false,
      "source_quote": "Based on training knowledge — verify against live policy"
    },
    "cross_site_tracking": {
      "value": false,
      "source_quote": "Based on training knowledge — verify against live policy"
    },
    "used_for_profiling": {
      "value": false,
      "source_quote": "Based on training knowledge — verify against live policy"
    },
    "used_to_train_ai": {
      "value": null,
      "source_quote": "Based on training knowledge — verify against live policy"
    }
  },
  "third_party_recipients": {
    "count": null,
    "count_type": "category-only",
    "categories": [
      "Mozilla contractors and service providers",
      "Search engine partners (for search data)",
      "Content delivery networks"
    ],
    "source_quote": "Based on training knowledge — verify against live policy"
  },
  "retention_period": {
    "value": "Telemetry data retained for 90 days; crash reports kept longer for analysis; users can disable collection",
    "source_quote": "Based on training knowledge — verify against live policy"
  },
  "your_rights": {
    "access_your_data": {
      "value": true,
      "source_quote": "Based on training knowledge — verify against live policy"
    },
    "delete_your_data": {
      "value": true,
      "source_quote": "Based on training knowledge — verify against live policy"
    },
    "correct_inaccuracies": {
      "value": null,
      "source_quote": "Based on training knowledge — verify against live policy"
    },
    "opt_out_of_sale_sharing": {
      "value": true,
      "source_quote": "Based on training knowledge — verify against live policy"
    },
    "data_portability": {
      "value": null,
      "source_quote": "Based on training knowledge — verify against live policy"
    },
    "appeal_decisions": {
      "value": null,
      "source_quote": "Based on training knowledge — verify against live policy"
    }
  },
  "security_measures": {
    "encrypted_in_transit": {
      "value": true,
      "source_quote": "Based on training knowledge — verify against live policy"
    },
    "encrypted_at_rest": {
      "value": true,
      "source_quote": "Based on training knowledge — verify against live policy"
    },
    "mfa_available": {
      "value": true,
      "source_quote": "Based on training knowledge — verify against live policy"
    },
    "breach_notification": {
      "value": true,
      "source_quote": "Based on training knowledge — verify against live policy"
    },
    "independent_audits": {
      "value": true,
      "source_quote": "Based on training knowledge — verify against live policy"
    }
  },
  "tracking_signals": {
    "honors_gpc": {
      "value": true,
      "source_quote": "Based on training knowledge — verify against live policy"
    },
    "honors_dnt": {
      "value": true,
      "source_quote": "Based on training knowledge — verify against live policy"
    }
  },
  "childrens_privacy": {
    "minimum_age": 13,
    "coppa_compliant": null,
    "notes": "Mozilla does not target children; standard privacy protections apply to all users.",
    "source_quote": "Based on training knowledge — verify against live policy"
  },
  "gaps": [
    "Data correction mechanisms not detailed",
    "Data portability process not specified",
    "AI training use not explicitly addressed"
  ],
  "label_notes": "Source: training knowledge. Firefox emphasizes privacy by default with minimal telemetry collection. Telemetry is opt-in and can be easily disabled. Mozilla is a non-profit organization committed to open-source principles. Strong support for privacy signals (GPC, DNT)."
}
